{
  "sections": {
    "main": {
      "type": "main-product",
      "blocks": {
        "vendor": {
          "type": "text",
          "settings": {
            "text": "<p>{{ product.vendor }}<\/p>",
            "text_style": "subtitle"
          }
        },
        "title": {
          "type": "title",
          "settings": {
          }
        },
        "price": {
          "type": "price",
          "settings": {
          }
        },
        "variant_picker": {
          "type": "variant_picker",
          "settings": {
            "show_variant_labels": true,
            "show_quantities": "no"
          }
        },
        "buy_buttons": {
          "type": "buy_buttons",
          "settings": {
            "show_dynamic_checkout": true,
            "show_quantity_selector": true
          }
        },
        "pickup_avaiability": {
          "type": "pickup_avaiability",
          "settings": {
          }
        },
        "description": {
          "type": "description",
          "settings": {
            "product_description_truncated": "truncated--disabled"
          }
        },
        "share": {
          "type": "share",
          "settings": {
          }
        }
      },
      "block_order": [
        "vendor",
        "title",
        "price",
        "variant_picker",
        "buy_buttons",
        "pickup_avaiability",
        "description",
        "share"
      ],
      "settings": {
        "gallery_style": "slider",
        "gallery_slider_style": true,
        "gallery_pagination": "dots",
        "gallery_gutter": false,
        "enable_zoom": true,
        "enable_video_looping": false
      }
    },
    "product-recommendations": {
      "type": "product-recommendations",
      "settings": {
        "heading": "You may also like"
      }
    },
    "16814605547b5fbff5": {
      "type": "apps",
      "blocks": {
        "b17e78ef-6877-497b-81e7-c9df9ac6d3d5": {
          "type": "shopify:\/\/apps\/wdt-fancy-image-gallery\/blocks\/app-block\/05b813ce-f90c-44cc-aa96-3aaac819e27d",
          "settings": {
            "wdt_image_code": "here is gallery"
          }
        }
      },
      "block_order": [
        "b17e78ef-6877-497b-81e7-c9df9ac6d3d5"
      ],
      "settings": {
        "gutter_enabled": true
      }
    }
  },
  "order": [
    "main",
    "product-recommendations",
    "16814605547b5fbff5"
  ]
}
